utilities.py
gearwall/Chem_Tools/__init__.py
gearwall/Chem_Tools/chem_utilities.py
gearwall/Chem_Tools/density_cube.py
gearwall/Chem_Tools/dvr.py
gearwall/Chem_Tools/dvr_arrays.py
gearwall/Chem_Tools/gaussian_tools.py
gearwall/Chem_Tools/misc.py
gearwall/Chem_Tools/test.py
gearwall/Chem_Tools/test_dvr.py
gearwall/Data_Tools/__init__.py
gearwall/Data_Tools/explore.py
gearwall/Data_Tools/model_tools.py
gearwall-0.1.1.dist-info/LICENSE
gearwall-0.1.1.dist-info/METADATA
gearwall-0.1.1.dist-info/WHEEL
gearwall-0.1.1.dist-info/top_level.txt
gearwall-0.1.1.dist-info/RECORD
