Metadata-Version: 2.1
Name: gearwall
Version: 0.1.1
Summary: My personal code, including simulation software, data analysis, and general utilities
Home-page: https://github.com/cgavinh/gearwall
Download-URL: https://pypi.org/project/gearwall/
Author: Coire Gavin-Hanner
Author-email: c.gavin.hanner@gmail.com
License: MIT
Keywords: Data,Analysis,Quantum
License-File: LICENSE
